Metadata-Version: 2.1
Name: pymastermind
Version: 1.2
Summary: A Python package designed to play, develop strategies/algorithms, and implement the classic MasterMind board game.
Home-page: https://github.com/thomasbreydo/pymastermind
Author: Thomas Breydo
Author-email: tbreydo@gmail.com
License: MIT
Download-URL: https://github.com/thomasbreydo/pymastermind/archive/v1.2.tar.gz
Keywords: GAME,MASTER,MIND,STRATEGY,BOARD,CODE
Platform: UNKNOWN
Classifier: Development Status :: 5 - Production/Stable
Classifier: Intended Audience :: Developers
Classifier: License :: OSI Approved :: MIT License
Classifier: Natural Language :: English
Classifier: Operating System :: OS Independent
Classifier: Programming Language :: Python :: 3.7
Classifier: Topic :: Games/Entertainment :: Board Games
Classifier: Topic :: Games/Entertainment :: Turn Based Strategy
